setup.py
dsnd_ml_nano_distributions/Binomialdistribution.py
dsnd_ml_nano_distributions/Gaussiandistribution.py
dsnd_ml_nano_distributions/Generaldistribution.py
dsnd_ml_nano_distributions/__init__.py
dsnd_ml_nano_distributions.egg-info/PKG-INFO
dsnd_ml_nano_distributions.egg-info/SOURCES.txt
dsnd_ml_nano_distributions.egg-info/dependency_links.txt
dsnd_ml_nano_distributions.egg-info/not-zip-safe
dsnd_ml_nano_distributions.egg-info/top_level.txt