Metadata-Version: 1.0
Name: dsnd-ml-nano-distributions
Version: 1.0
Summary: Gaussian distributions, Binomial distributions
Home-page: UNKNOWN
Author: Isaac Tan
Author-email: UNKNOWN
License: UNKNOWN
Platform: UNKNOWN
